lsdttparamselector/__init__.py
lsdttparamselector/lsdttparamselector.py
lsdttparamselector-0.2.0.dist-info/AUTHORS.rst
lsdttparamselector-0.2.0.dist-info/LICENSE
lsdttparamselector-0.2.0.dist-info/METADATA
lsdttparamselector-0.2.0.dist-info/WHEEL
lsdttparamselector-0.2.0.dist-info/top_level.txt
lsdttparamselector-0.2.0.dist-info/RECORD
