Metadata-Version: 2.1
Name: lsdttparamselector
Version: 0.2.0
Summary: A small package using ipython widgets that allows users to select parameters from menus. These can be passed to another object in lsdviztools to create a driver file for the lsdtopotools command line tools.
Home-page: https://github.com/simon-m-mudd/lsdttparamselector
Author: Simon M Mudd
Author-email: simon.m.mudd@ed.ac.uk
License: MIT license
Keywords: lsdttparamselector
Platform: UNKNOWN
Classifier: Development Status :: 2 - Pre-Alpha
Classifier: Intended Audience :: Developers
Classifier: License :: OSI Approved :: MIT License
Classifier: Natural Language :: English
Classifier: Programming Language :: Python :: 3
Classifier: Programming Language :: Python :: 3.5
Classifier: Programming Language :: Python :: 3.6
Classifier: Programming Language :: Python :: 3.7
Classifier: Programming Language :: Python :: 3.8
Requires-Python: >=3.5
Requires-Dist: ipykernel
Requires-Dist: ipython
Requires-Dist: ipywidgets
